text_cleaner/__init__.py
text_cleaner/cleaner.py
lf_text_cleaner-0.0.2.dist-info/METADATA
lf_text_cleaner-0.0.2.dist-info/WHEEL
lf_text_cleaner-0.0.2.dist-info/top_level.txt
lf_text_cleaner-0.0.2.dist-info/RECORD
