Metadata-Version: 2.1
Name: lf_text_cleaner
Version: 0.0.2
Summary: A simple text cleaning package for preprocessing text data
Author: Amir Hossein
Author-email: ah.gholami2000@gmail.com
Keywords: text cleaning preprocessing
Classifier: Programming Language :: Python :: 3
Classifier: License :: OSI Approved :: MIT License
Classifier: Operating System :: OS Independent
Requires-Python: >=3.6
